README
setup.py
biofrills/__init__.py
biofrills/alnutils.py
biofrills/consensus.py
biofrills/cpairutils.c
biofrills/cpairutils.pyx
biofrills/logoutils.py
biofrills/pairutils.py
biofrills/sequtils.py
biofrills.egg-info/PKG-INFO
biofrills.egg-info/SOURCES.txt
biofrills.egg-info/dependency_links.txt
biofrills.egg-info/requires.txt
biofrills.egg-info/top_level.txt
biofrills/stats/__init__.py
biofrills/stats/chisq.py