Metadata-Version: 1.1
Name: biofrills
Version: 0.3.1
Summary: Bioinformatics utilities for molecular sequence analysis.
Home-page: http://github.com/etal/biofrills
Author: Eric Talevich
Author-email: eric.talevich@gmail.com
License: UNKNOWN
Platform: UNKNOWN
Classifier: Development Status :: 4 - Beta
Classifier: Intended Audience :: Developers
Classifier: Intended Audience :: Science/Research
Classifier: License :: OSI Approved :: BSD License
Classifier: Programming Language :: Python :: 2.7
Classifier: Programming Language :: Python :: Implementation :: PyPy
Classifier: Topic :: Scientific/Engineering :: Bio-Informatics
